<?xml version="1.0" encoding="UTF-8"?>
<mxGraphModel dx="2349" dy="1403" grid="1" gridSize="10" guides="1" tooltips="1" connect="1" arrows="1" fold="1" page="1" pageScale="1" pageWidth="1169" pageHeight="827" math="0" shadow="0"><root><mxCell id="0"/><mxCell id="1" parent="0"/><mxCell id="EK3cA5FGlJivAC3kWu5P-48" value="saveHighScore" style="text;html=1;resizable=0;points=[];autosize=1;align=left;verticalAlign=top;spacingTop=-4;" parent="1" vertex="1"><mxGeometry x="-487" y="-448.5" width="100" height="10" as="geometry"/></mxCell><mxCell id="EK3cA5FGlJivAC3kWu5P-21" style="edgeStyle=orthogonalEdgeStyle;rounded=0;orthogonalLoop=1;jettySize=auto;html=1;" parent="1" source="EK3cA5FGlJivAC3kWu5P-1" target="EK3cA5FGlJivAC3kWu5P-14" edge="1"><mxGeometry relative="1" as="geometry"><Array as="points"><mxPoint x="-460" y="-520"/><mxPoint x="-460" y="-520"/></Array></mxGeometry></mxCell><mxCell id="EK3cA5FGlJivAC3kWu5P-46" style="edgeStyle=orthogonalEdgeStyle;rounded=0;orthogonalLoop=1;jettySize=auto;html=1;" parent="1" source="EK3cA5FGlJivAC3kWu5P-1" target="EK3cA5FGlJivAC3kWu5P-14" edge="1"><mxGeometry relative="1" as="geometry"><Array as="points"><mxPoint x="-450" y="-454"/><mxPoint x="-450" y="-454"/></Array></mxGeometry></mxCell><mxCell id="EK3cA5FGlJivAC3kWu5P-1" value="MenuController&lt;br&gt;" style="swimlane;fontStyle=1;align=center;verticalAlign=top;childLayout=stackLayout;horizontal=1;startSize=26;horizontalStack=0;resizeParent=1;resizeParentMax=0;resizeLast=0;collapsible=1;marginBottom=0;html=1;" parent="1" vertex="1"><mxGeometry x="-945" y="-624" width="395" height="340" as="geometry"/></mxCell><mxCell id="EK3cA5FGlJivAC3kWu5P-2" value="&#10;&#10;" style="text;strokeColor=none;fillColor=none;align=left;verticalAlign=top;spacingLeft=4;spacingRight=4;overflow=hidden;rotatable=0;points=[[0,0.5],[1,0.5]];portConstraint=eastwest;" parent="EK3cA5FGlJivAC3kWu5P-1" vertex="1"><mxGeometry y="26" width="395" height="34" as="geometry"/></mxCell><mxCell id="EK3cA5FGlJivAC3kWu5P-3" value="" style="line;strokeWidth=1;fillColor=none;align=left;verticalAlign=middle;spacingTop=-1;spacingLeft=3;spacingRight=3;rotatable=0;labelPosition=right;points=[];portConstraint=eastwest;" parent="EK3cA5FGlJivAC3kWu5P-1" vertex="1"><mxGeometry y="60" width="395" height="8" as="geometry"/></mxCell><mxCell id="EK3cA5FGlJivAC3kWu5P-4" value="&lt;constructor&gt; + MenuController(viewUi: View::Ui*,&#10;                                                    menuModel : MenuModel*)&#10;+ ~MenuController()&#10;&#10;signals:&#10;+ addRecordToHighScore(newPlayerScoreRecord : PlayerScore) : void&#10;+ saveHighScore() : void&#10;&#10;slots:&#10;+ startGame() : void&#10;+ gameOver() : void&#10;+ highScore() : void&#10;+ back() : void&#10;+ save(newPlayerScore : PlayerScore) : void&#10;+ updateHighScore(highScoreIterator : QList&lt;PlayerScore&gt;::iterator,&#10;                                size : int) : void&#10;+ quit() : void&#10;" style="text;strokeColor=none;fillColor=none;align=left;verticalAlign=top;spacingLeft=4;spacingRight=4;overflow=hidden;rotatable=0;points=[[0,0.5],[1,0.5]];portConstraint=eastwest;" parent="EK3cA5FGlJivAC3kWu5P-1" vertex="1"><mxGeometry y="68" width="395" height="272" as="geometry"/></mxCell><mxCell id="EK3cA5FGlJivAC3kWu5P-18" style="edgeStyle=orthogonalEdgeStyle;rounded=0;orthogonalLoop=1;jettySize=auto;html=1;" parent="1" source="EK3cA5FGlJivAC3kWu5P-5" target="EK3cA5FGlJivAC3kWu5P-1" edge="1"><mxGeometry relative="1" as="geometry"><Array as="points"><mxPoint x="-995" y="-420.5"/><mxPoint x="-995" y="-420.5"/></Array></mxGeometry></mxCell><mxCell id="EK3cA5FGlJivAC3kWu5P-5" value="PlayerController&lt;br&gt;" style="swimlane;fontStyle=1;align=center;verticalAlign=top;childLayout=stackLayout;horizontal=1;startSize=26;horizontalStack=0;resizeParent=1;resizeParentMax=0;resizeLast=0;collapsible=1;marginBottom=0;html=1;" parent="1" vertex="1" collapsed="1"><mxGeometry x="-1160" y="-433.5" width="120" height="26" as="geometry"><mxRectangle x="-1200" y="-440" width="390" height="260" as="alternateBounds"/></mxGeometry></mxCell><mxCell id="EK3cA5FGlJivAC3kWu5P-6" value="&#10;&#10;" style="text;strokeColor=none;fillColor=none;align=left;verticalAlign=top;spacingLeft=4;spacingRight=4;overflow=hidden;rotatable=0;points=[[0,0.5],[1,0.5]];portConstraint=eastwest;" parent="EK3cA5FGlJivAC3kWu5P-5" vertex="1"><mxGeometry y="26" width="120" height="24" as="geometry"/></mxCell><mxCell id="EK3cA5FGlJivAC3kWu5P-7" value="" style="line;strokeWidth=1;fillColor=none;align=left;verticalAlign=middle;spacingTop=-1;spacingLeft=3;spacingRight=3;rotatable=0;labelPosition=right;points=[];portConstraint=eastwest;" parent="EK3cA5FGlJivAC3kWu5P-5" vertex="1"><mxGeometry y="50" width="120" height="8" as="geometry"/></mxCell><mxCell id="EK3cA5FGlJivAC3kWu5P-8" value="&lt;constructor&gt; + PlayerController(player : Player*,&#10;                                                     healthView : HealthView* )&#10;+ ~PlayerController()&#10;&#10;signals:&#10;+ changePlayerAtribute(specialType : enum) : void&#10;+ changeHealth(value : int) : void&#10;+ playerDefeated() : void&#10;&#10;slots:&#10;+ changeHealth(value : int) : void&#10;+ changePlayerAtribute(specialType : enum) : void&#10;+ playerDefeated() : void&#10;&#10;" style="text;strokeColor=none;fillColor=none;align=left;verticalAlign=top;spacingLeft=4;spacingRight=4;overflow=hidden;rotatable=0;points=[[0,0.5],[1,0.5]];portConstraint=eastwest;" parent="EK3cA5FGlJivAC3kWu5P-5" vertex="1"><mxGeometry y="58" width="120" height="202" as="geometry"/></mxCell><mxCell id="EK3cA5FGlJivAC3kWu5P-28" style="edgeStyle=orthogonalEdgeStyle;rounded=0;orthogonalLoop=1;jettySize=auto;html=1;" parent="1" source="EK3cA5FGlJivAC3kWu5P-9" target="EK3cA5FGlJivAC3kWu5P-1" edge="1"><mxGeometry relative="1" as="geometry"><Array as="points"><mxPoint x="-890" y="-230"/><mxPoint x="-890" y="-230"/></Array></mxGeometry></mxCell><mxCell id="EK3cA5FGlJivAC3kWu5P-31" style="edgeStyle=orthogonalEdgeStyle;rounded=0;orthogonalLoop=1;jettySize=auto;html=1;" parent="1" source="EK3cA5FGlJivAC3kWu5P-9" target="EK3cA5FGlJivAC3kWu5P-1" edge="1"><mxGeometry relative="1" as="geometry"><Array as="points"><mxPoint x="-790" y="-220"/><mxPoint x="-790" y="-220"/></Array></mxGeometry></mxCell><mxCell id="EK3cA5FGlJivAC3kWu5P-34" style="edgeStyle=orthogonalEdgeStyle;rounded=0;orthogonalLoop=1;jettySize=auto;html=1;" parent="1" source="EK3cA5FGlJivAC3kWu5P-9" target="EK3cA5FGlJivAC3kWu5P-1" edge="1"><mxGeometry relative="1" as="geometry"><Array as="points"><mxPoint x="-720" y="-220"/><mxPoint x="-720" y="-220"/></Array></mxGeometry></mxCell><mxCell id="EK3cA5FGlJivAC3kWu5P-35" style="edgeStyle=orthogonalEdgeStyle;rounded=0;orthogonalLoop=1;jettySize=auto;html=1;" parent="1" source="EK3cA5FGlJivAC3kWu5P-9" target="EK3cA5FGlJivAC3kWu5P-1" edge="1"><mxGeometry relative="1" as="geometry"><Array as="points"><mxPoint x="-650" y="-210"/><mxPoint x="-650" y="-210"/></Array></mxGeometry></mxCell><mxCell id="EK3cA5FGlJivAC3kWu5P-43" style="edgeStyle=orthogonalEdgeStyle;rounded=0;orthogonalLoop=1;jettySize=auto;html=1;" parent="1" source="EK3cA5FGlJivAC3kWu5P-9" target="EK3cA5FGlJivAC3kWu5P-1" edge="1"><mxGeometry relative="1" as="geometry"><Array as="points"><mxPoint x="-580" y="-210"/><mxPoint x="-580" y="-210"/></Array></mxGeometry></mxCell><mxCell id="EK3cA5FGlJivAC3kWu5P-9" value="View" style="swimlane;fontStyle=1;align=center;verticalAlign=top;childLayout=stackLayout;horizontal=1;startSize=26;horizontalStack=0;resizeParent=1;resizeParentMax=0;resizeLast=0;collapsible=1;marginBottom=0;" parent="1" vertex="1" collapsed="1"><mxGeometry x="-926.5" y="-138" width="373" height="26" as="geometry"><mxRectangle x="-870" y="-190" width="300" height="130" as="alternateBounds"/></mxGeometry></mxCell><mxCell id="EK3cA5FGlJivAC3kWu5P-10" value="+ ui: Ui::GalacticWar&#10;+ scene: QGraphicsScene&#10;" style="text;strokeColor=none;fillColor=none;align=left;verticalAlign=top;spacingLeft=4;spacingRight=4;overflow=hidden;rotatable=0;points=[[0,0.5],[1,0.5]];portConstraint=eastwest;" parent="EK3cA5FGlJivAC3kWu5P-9" vertex="1"><mxGeometry y="26" width="373" height="44" as="geometry"/></mxCell><mxCell id="EK3cA5FGlJivAC3kWu5P-11" value="" style="line;strokeWidth=1;fillColor=none;align=left;verticalAlign=middle;spacingTop=-1;spacingLeft=3;spacingRight=3;rotatable=0;labelPosition=right;points=[];portConstraint=eastwest;" parent="EK3cA5FGlJivAC3kWu5P-9" vertex="1"><mxGeometry y="70" width="373" height="20" as="geometry"/></mxCell><mxCell id="EK3cA5FGlJivAC3kWu5P-12" value="&lt;constructor&gt; + View(parent : QWidget*)&#10;+ ~View()&#10;" style="text;strokeColor=none;fillColor=none;align=left;verticalAlign=top;spacingLeft=4;spacingRight=4;overflow=hidden;rotatable=0;points=[[0,0.5],[1,0.5]];portConstraint=eastwest;" parent="EK3cA5FGlJivAC3kWu5P-9" vertex="1"><mxGeometry y="90" width="373" height="40" as="geometry"/></mxCell><mxCell id="EK3cA5FGlJivAC3kWu5P-49" style="edgeStyle=orthogonalEdgeStyle;rounded=0;orthogonalLoop=1;jettySize=auto;html=1;" parent="1" source="EK3cA5FGlJivAC3kWu5P-14" target="EK3cA5FGlJivAC3kWu5P-1" edge="1"><mxGeometry relative="1" as="geometry"><Array as="points"><mxPoint x="-430" y="-390"/><mxPoint x="-430" y="-390"/></Array></mxGeometry></mxCell><mxCell id="EK3cA5FGlJivAC3kWu5P-14" value="MenuModel&lt;br&gt;" style="swimlane;fontStyle=1;align=center;verticalAlign=top;childLayout=stackLayout;horizontal=1;startSize=26;horizontalStack=0;resizeParent=1;resizeParentMax=0;resizeLast=0;collapsible=1;marginBottom=0;html=1;" parent="1" vertex="1"><mxGeometry x="-400" y="-566" width="380" height="240" as="geometry"/></mxCell><mxCell id="EK3cA5FGlJivAC3kWu5P-15" value="- highScoreList : QList&lt;PlayerScore&gt;" style="text;strokeColor=none;fillColor=none;align=left;verticalAlign=top;spacingLeft=4;spacingRight=4;overflow=hidden;rotatable=0;points=[[0,0.5],[1,0.5]];portConstraint=eastwest;" parent="EK3cA5FGlJivAC3kWu5P-14" vertex="1"><mxGeometry y="26" width="380" height="24" as="geometry"/></mxCell><mxCell id="EK3cA5FGlJivAC3kWu5P-16" value="" style="line;strokeWidth=1;fillColor=none;align=left;verticalAlign=middle;spacingTop=-1;spacingLeft=3;spacingRight=3;rotatable=0;labelPosition=right;points=[];portConstraint=eastwest;" parent="EK3cA5FGlJivAC3kWu5P-14" vertex="1"><mxGeometry y="50" width="380" height="8" as="geometry"/></mxCell><mxCell id="EK3cA5FGlJivAC3kWu5P-17" value="&lt;constructor&gt; + MenuModel()&#10;+ ~MenuModel()&#10;- loadHighScore() : void&#10;&#10;signals:&#10;+ updateHighScore(highScoreIterator : QList&lt;PlayerScore&gt;::iterator,&#10;                                size : int) : void&#10;&#10;slots:&#10;+ addRecordToHighScore(newPlayerScore : PlayerScore) : void&#10;+ saveHighScore() : void&#10;" style="text;strokeColor=none;fillColor=none;align=left;verticalAlign=top;spacingLeft=4;spacingRight=4;overflow=hidden;rotatable=0;points=[[0,0.5],[1,0.5]];portConstraint=eastwest;" parent="EK3cA5FGlJivAC3kWu5P-14" vertex="1"><mxGeometry y="58" width="380" height="182" as="geometry"/></mxCell><mxCell id="EK3cA5FGlJivAC3kWu5P-19" value="playerDefeated" style="text;html=1;resizable=0;points=[];autosize=1;align=left;verticalAlign=top;spacingTop=-4;" parent="1" vertex="1"><mxGeometry x="-1040" y="-438.5" width="100" height="10" as="geometry"/></mxCell><mxCell id="EK3cA5FGlJivAC3kWu5P-20" value="gameOver" style="text;html=1;resizable=0;points=[];autosize=1;align=left;verticalAlign=top;spacingTop=-4;" parent="1" vertex="1"><mxGeometry x="-1005" y="-414.5" width="70" height="10" as="geometry"/></mxCell><mxCell id="EK3cA5FGlJivAC3kWu5P-22" value="addRecordToHighScore&lt;br&gt;" style="text;html=1;resizable=0;points=[];autosize=1;align=left;verticalAlign=top;spacingTop=-4;" parent="1" vertex="1"><mxGeometry x="-550" y="-538.5" width="140" height="10" as="geometry"/></mxCell><mxCell id="EK3cA5FGlJivAC3kWu5P-23" value="addRecordToHighScore" style="text;html=1;resizable=0;points=[];autosize=1;align=left;verticalAlign=top;spacingTop=-4;" parent="1" vertex="1"><mxGeometry x="-530" y="-517.5" width="140" height="10" as="geometry"/></mxCell><mxCell id="EK3cA5FGlJivAC3kWu5P-26" value="&lt;span&gt;MenuController&lt;/span&gt;" style="shape=umlFrame;whiteSpace=wrap;html=1;width=95;height=30;" parent="1" vertex="1"><mxGeometry x="-1160" y="-810" width="1150" height="790" as="geometry"/></mxCell><mxCell id="EK3cA5FGlJivAC3kWu5P-29" value="startGame" style="text;html=1;resizable=0;points=[];autosize=1;align=left;verticalAlign=top;spacingTop=-4;" parent="1" vertex="1"><mxGeometry x="-955" y="-158.5" width="70" height="10" as="geometry"/></mxCell><mxCell id="EK3cA5FGlJivAC3kWu5P-30" value="startGame" style="text;html=1;resizable=0;points=[];autosize=1;align=left;verticalAlign=top;spacingTop=-4;" parent="1" vertex="1"><mxGeometry x="-955" y="-272.5" width="70" height="10" as="geometry"/></mxCell><mxCell id="EK3cA5FGlJivAC3kWu5P-32" value="highScore" style="text;html=1;resizable=0;points=[];autosize=1;align=left;verticalAlign=top;spacingTop=-4;" parent="1" vertex="1"><mxGeometry x="-850" y="-157.5" width="70" height="10" as="geometry"/></mxCell><mxCell id="EK3cA5FGlJivAC3kWu5P-33" value="highScore" style="text;html=1;resizable=0;points=[];autosize=1;align=left;verticalAlign=top;spacingTop=-4;" parent="1" vertex="1"><mxGeometry x="-850" y="-271.5" width="70" height="10" as="geometry"/></mxCell><mxCell id="EK3cA5FGlJivAC3kWu5P-36" value="save" style="text;html=1;resizable=0;points=[];autosize=1;align=left;verticalAlign=top;spacingTop=-4;" parent="1" vertex="1"><mxGeometry x="-750" y="-159.5" width="40" height="10" as="geometry"/></mxCell><mxCell id="EK3cA5FGlJivAC3kWu5P-37" value="save" style="text;html=1;resizable=0;points=[];autosize=1;align=left;verticalAlign=top;spacingTop=-4;" parent="1" vertex="1"><mxGeometry x="-750" y="-272.5" width="40" height="10" as="geometry"/></mxCell><mxCell id="EK3cA5FGlJivAC3kWu5P-39" value="back" style="text;html=1;resizable=0;points=[];autosize=1;align=left;verticalAlign=top;spacingTop=-4;" parent="1" vertex="1"><mxGeometry x="-680" y="-159.5" width="40" height="10" as="geometry"/></mxCell><mxCell id="EK3cA5FGlJivAC3kWu5P-42" value="back" style="text;html=1;resizable=0;points=[];autosize=1;align=left;verticalAlign=top;spacingTop=-4;" parent="1" vertex="1"><mxGeometry x="-680" y="-271.5" width="40" height="10" as="geometry"/></mxCell><mxCell id="EK3cA5FGlJivAC3kWu5P-44" value="quit" style="text;html=1;resizable=0;points=[];autosize=1;align=left;verticalAlign=top;spacingTop=-4;" parent="1" vertex="1"><mxGeometry x="-610" y="-159.5" width="40" height="10" as="geometry"/></mxCell><mxCell id="EK3cA5FGlJivAC3kWu5P-45" value="quit" style="text;html=1;resizable=0;points=[];autosize=1;align=left;verticalAlign=top;spacingTop=-4;" parent="1" vertex="1"><mxGeometry x="-610" y="-272.5" width="40" height="10" as="geometry"/></mxCell><mxCell id="EK3cA5FGlJivAC3kWu5P-47" value="saveHighScore" style="text;html=1;resizable=0;points=[];autosize=1;align=left;verticalAlign=top;spacingTop=-4;" parent="1" vertex="1"><mxGeometry x="-550" y="-474" width="100" height="10" as="geometry"/></mxCell><mxCell id="EK3cA5FGlJivAC3kWu5P-50" value="updateHighScore" style="text;html=1;resizable=0;points=[];autosize=1;align=left;verticalAlign=top;spacingTop=-4;" parent="1" vertex="1"><mxGeometry x="-500" y="-408" width="110" height="10" as="geometry"/></mxCell><mxCell id="EK3cA5FGlJivAC3kWu5P-51" value="updateHighScore" style="text;html=1;resizable=0;points=[];autosize=1;align=left;verticalAlign=top;spacingTop=-4;" parent="1" vertex="1"><mxGeometry x="-550" y="-388" width="110" height="10" as="geometry"/></mxCell></root></mxGraphModel>